hands_on_ai/__init__.py
hands_on_ai/cli.py
hands_on_ai/config.py
hands_on_ai/models.py
hands_on_ai/agent/__init__.py
hands_on_ai/agent/cli.py
hands_on_ai/agent/core.py
hands_on_ai/agent/formats.py
hands_on_ai/agent/prompts.py
hands_on_ai/agent/schemas.py
hands_on_ai/agent/tools.py
hands_on_ai/agent/web.py
hands_on_ai/agent/agents/__init__.py
hands_on_ai/agent/agents/calculator.py
hands_on_ai/agent/agents/converter.py
hands_on_ai/agent/agents/datetime_tools.py
hands_on_ai/agent/agents/dictionary.py
hands_on_ai/agent/agents/education_tools.py
hands_on_ai/agent/agents/text_tools.py
hands_on_ai/agent/commands/__init__.py
hands_on_ai/agent/commands/ask.py
hands_on_ai/agent/commands/interactive.py
hands_on_ai/agent/commands/tools.py
hands_on_ai/agent/commands/web.py
hands_on_ai/agent/tools/__init__.py
hands_on_ai/agent/tools/calculator.py
hands_on_ai/agent/tools/search.py
hands_on_ai/agent/tools/weather.py
hands_on_ai/chat/__init__.py
hands_on_ai/chat/bots.py
hands_on_ai/chat/cli.py
hands_on_ai/chat/get_response.py
hands_on_ai/chat/personalities.py
hands_on_ai/chat/commands/__init__.py
hands_on_ai/chat/commands/ask.py
hands_on_ai/chat/commands/bots.py
hands_on_ai/chat/commands/doctor.py
hands_on_ai/chat/commands/interactive.py
hands_on_ai/chat/commands/web.py
hands_on_ai/chat/data/fallbacks.json
hands_on_ai/chat/personalities/__init__.py
hands_on_ai/chat/personalities/creative.py
hands_on_ai/chat/personalities/educational.py
hands_on_ai/chat/personalities/friendly.py
hands_on_ai/chat/personalities/sarcastic.py
hands_on_ai/chat/personalities/technical.py
hands_on_ai/chat/personalities/template.py
hands_on_ai/chat/personalities/therapeutic.py
hands_on_ai/chat/personalities/bots/__init__.py
hands_on_ai/chat/personalities/bots/coder_bot.py
hands_on_ai/chat/personalities/bots/friendly_bot.py
hands_on_ai/chat/personalities/bots/pirate_bot.py
hands_on_ai/chat/personalities/bots/sarcastic_bot.py
hands_on_ai/chat/personalities/bots/shakespeare_bot.py
hands_on_ai-0.2.0.dist-info/entry_points.txt
hands_on_ai-0.2.0.dist-info/licenses/LICENSE
hands_on_ai-0.2.0.dist-info/WHEEL
hands_on_ai-0.2.0.dist-info/METADATA
hands_on_ai-0.2.0.dist-info/RECORD
