Metadata-Version: 2.4
Name: hands-on-ai
Version: 0.2.0
Summary: Hands-on AI Toolkit for classrooms
Author-email: Michael Borck <michael@borck.me>
Requires-Python: >=3.10
License-File: LICENSE
Requires-Dist: requests
Requires-Dist: typer
Requires-Dist: python-fasthtml
Requires-Dist: python-docx
Requires-Dist: pymupdf
Requires-Dist: scikit-learn
Requires-Dist: numpy
Requires-Dist: instructor>=1.11.0
Requires-Dist: pydantic>=2.0
Requires-Dist: pytest ; extra == "dev"
Requires-Dist: build ; extra == "dev"
Requires-Dist: twine==6.0.1 ; extra == "dev"
Requires-Dist: cython ; extra == "dev"
Requires-Dist: ruff ; extra == "dev"
Requires-Dist: mkdocs ; extra == "dev"
Requires-Dist: mkdocstrings[python] ; extra == "dev"
Requires-Dist: mkdocs-material ; extra == "dev"
Requires-Dist: pymdown-extensions ; extra == "dev"
Requires-Dist: uv ; extra == "dev"
Project-URL: Documentation, https://michael-borck.github.io/hands-on-ai/
Project-URL: Homepage, https://github.com/teaching-repositories/hands-on-ai
Project-URL: Issues, https://github.com/teaching-repositories/hands-on-ai
Project-URL: Source, https://github.com/teaching-repositories/hands-on-ai
Provides-Extra: agent
Provides-Extra: chat
Provides-Extra: dev
Provides-Extra: rag
